{"Q4148511": "E. F. Grekulov", "Q4148830": "Vladimir Greshnov", "Q4148886": "Vladimir Gribkov", "Q4148943": "Vyacheslav Gribovsky", "Q4149026": "Grigor Daranagetsi", "Q4149124": "Konstantin Grigorovich", "Q4149231": "Aleksandr Grigoryev", "Q4149344": "Jelena Grigorjeva", "Q4149397": "Ashot Grigoryan", "Q4149437": "Samvel Grigoryan", "Q4149544": "Ervin Grimm", "Q4149578": "Zakhar Grinberg", "Q4128855": "Valentin Vydrin", "Q4129225": "Leonid Vyskochkov", "Q4130218": "Terenty Vyazemsky", "Q4130454": "Vasiliy Vyatkin", "Q4130869": "Malik Gabdullin", "Q4130894": "Marcu Gabinschi", "Q4130955": "Aleksandr Gabrichevsky", "Q4131118": "Konstantin Gavrilin", "Q4131178": "Matvey Gavrilov", "Q4131514": "Kamaludin Gadzhiyev", "Q4131527": "Sani Tofiq o\u011flu Hac\u0131yev", "Q4131533": "Ninel Zeynalovna Gadzjieva", "Q4131535": "Sakinat Shikhamedovna Gadzhieva", "Q4131559": "Aleksandr Gadlo", "Q4131842": "Boris G\u0103in\u0103", "Q4132104": "Vladimir Gak", "Q4132107": "Dzhabrail Gakayev", "Q4132204": "Anatoly Galaktionov", "Q4132217": "Piotr Galanza", "Q4132332": "Yury Galenovich", "Q4132456": "Lev Galin", "Q4132460": "Fanour Galine", "Q4132497": "Rawil Wa\u011fiz u\u011fl\u0131 \u011ealiullin", "Q4132498": "Zagidulla Galiullin", "Q4132683": "Eugene V. Gallagher", "Q4132789": "Petr Galuzo", "Q4132939": "Ishmukhamet Galyautdinov", "Q4132972": "Oksana Gaman-Golutvina", "Q4133049": "Gadzhi Gamzatov", "Q4133220": "Vladimir Gander", "Q4133259": "Rafail Ganelin", "Q4133301": "Rivner Ganiyev", "Q4133380": "Khalida Gantseva", "Q4133493": "Andrei Victorovich Gaponov-Grekhov", "Q4133546": "Svetlana Garanina", "Q4133741": "Talmas Magsoemovitsj Garipov", "Q4134041": "Magomed Gasanov", "Q4134332": "Arif M\u0259mm\u0259d o\u011flu H\u0259\u015fimov", "Q4134533": "E. V. Gvozdev", "Q4134842": "von Heim Bernhard Andreas", "Q4135026": "Tamara Gella", "Q4135053": "Viktor Gelovani", "Q4135099": "Nison Gelperin", "Q4135222": "Alexander Gendin", "Q4135464": "Anatoli Guenko", "Q4136001": "Boris Gerasimov", "Q4136099": "Anatoly Gerashchenko", "Q4137137": "Victor Gergel", "Q4137146": "Aleksandr Gerd", "Q4137191": "Gennady Gering", "Q4137565": "Aleksey Gertsenson", "Q4137606": "David Efimovitsj Gersjanovitsj", "Q4137648": "Grigoriy Viktorovitsj Gersjoeni", "Q4137877": "Mikhail Gzovsky", "Q4138214": "Marietta Gize", "Q4138393": "\u0130sk\u00e4nd\u00e4r \u011eil\u00e4cef", "Q4138404": "Rudhzero Gilyarevskyi", "Q4138606": "Leonid Gindin", "Q4138642": "S. S. Ginzburg", "Q4138822": "Alexey Gippius", "Q4138966": "Leonard Girshman", "Q4138974": "Sergey Girko", "Q4139255": "Yevgeny Glagolev", "Q4139260": "Olga Glagoleva", "Q4139488": "Sergey Glazunov", "Q4139599": "Ivan Glebov", "Q4139600": "Igor Glebov", "Q4139768": "Vladislav Glinka", "Q4206772": "Vladimir Kabyshev", "Q4206932": "Afanasy Kaverznev", "Q4207099": "Matvey Kagan", "Q4207402": "Kadyrgaly Zhalairi", "Q4207469": "Bernard Kazhinskiy", "Q4207471": "Aleksandr Kazhikhov", "Q4207564": "Mikhail Kazakov", "Q4207758": "Boris Kazansky", "Q4207767": "Peter Evgen\u02b9evich Kazansky", "Q4207768": "Pyotr Kazansky", "Q4207770": "Pyotr Kazansky", "Q4207892": "Leonid Kazantsev", "Q4207903": "Yury Kazantsev", "Q4207906": "Tamara Kazantseva", "Q4208479": "Marcus Morton Rhoades", "Q4208494": "Olga Kazmina", "Q4208916": "Aleksandr Kakovkin", "Q4209144": "Anatoly Kalashnik", "Q4209152": "Vasily Kalashnikov", "Q4209235": "Gleb Kaleda"}