{"Q11632809": "Heiz\u014d Taniyama", "Q11632955": "Michiya Tanimoto", "Q11633014": "Tamaki Yaji", "Q11633035": "Hisayuki Tanizawa", "Q11633094": "Sh\u014dz\u014d Tanifuji", "Q11633479": "Hidenori Toyooka", "Q11634478": "Yasuko Kainuma", "Q11635728": "Shigeru Akamatsu", "Q11636921": "Adachi Nobuakira", "Q11638691": "Hisashi Kond\u014d", "Q11638793": "Yasuo Kond\u014d", "Q11638956": "Shunsuke Kond\u014d", "Q11642001": "Motomichi T\u014dyama", "Q11644061": "Hiroshi Sakai", "Q11644193": "Toshio Sakai", "Q11645812": "Oktay Efendiyev", "Q11645816": "Naoko Nomizo", "Q11646814": "Masami Kaneko", "Q11646918": "Yong-un Kim", "Q11647692": "Akihiko Kaneta", "Q11648730": "K\u014dji Suzuki", "Q11648902": "Sh\u014dichi Suzuki", "Q11648948": "Matsumi Suzuki", "Q11649152": "Akio Suzuki", "Q11649156": "Atsuyuki Suzuki", "Q11649316": "Tatsujir\u014d Suzuki", "Q11649325": "Kunihiko Suzuki", "Q11649328": "Kunio Suzuki", "Q11649391": "Masatsugu Suzuki", "Q11653510": "Mitsuo Nagamachi", "Q11653725": "Tooru Hasegawa", "Q11653953": "Miki Hasegawa", "Q11655115": "Hideki Monma", "Q11655297": "Y\u016bji Hiraki", "Q11655622": "Tadashi Sekiguchi", "Q11655840": "Naoto Sekimura", "Q11656411": "Takao Sekiya", "Q11659543": "Tsuneo Nanba", "Q11661226": "Chiharu Aoyama", "Q11661245": "Masahide Aoyama", "Q11661601": "Mika Aoki", "Q11661674": "Kazuhiko Aoki", "Q11661873": "Michiyoshi Aoki", "Q11662800": "Toshihiro Aono", "Q11664654": "Takashi Suda", "Q11665663": "Shunsuke Kazama", "Q11666133": "Atsuo Iiyoshi", "Q11666397": "T\u014dru Iijima", "Q11666475": "Hitoshi Iida", "Q11666500": "Yoshihiro Iida", "Q11668924": "Shigeo Takahara", "Q11670071": "Noboru Takagi", "Q11670970": "Reiko Takahashi", "Q11671308": "Akira Takahashi", "Q11671473": "Mutsumasa Takahashi", "Q11671571": "Takahashi Yoshitoki", "Q11671615": "Yutaka Takahashi", "Q11671938": "Sachiko Takase", "Q11672108": "K\u014dji Takada", "Q11673950": "Jun Uozumi", "Q11674152": "K\u014dichi Ayuta", "Q11675296": "Hidetar\u014d H\u014d", "Q11678106": "Tamotsu Kuroiwa", "Q11678211": "Kurokawa Kaneyuki", "Q15845883": "Nikolay Olegovich Milanov", "Q15845911": "Konstantin Strakhovich", "Q15848292": "Juliet Gerrard", "Q15877364": "Katherine Luzuriaga", "Q15883033": "Yauhien Anischanka", "Q15894235": "Gottlob Friedrich Wilhelm Juncker", "Q15914021": "Jiang Minhua", "Q15918749": "Victor Emanuel Levine", "Q15918932": "Viktor Struchkov", "Q15921637": "Pan Wen-Yuan", "Q15927206": "Sinske Hattori", "Q15934288": "Chen Fuliang", "Q15940639": "LO, Yuen Tze", "Q15955121": "Christian Gotfried Hummel", "Q15960574": "Almaz Sharman", "Q15965793": "Aleksey Gagarin", "Q15965857": "Vladimir Kuznetsov", "Q15965870": "Nagim Isjbulatov", "Q15965956": "Yuri Vysheslavtsev", "Q15965974": "Vladimir Leonidovich Kleyman", "Q15966025": "Yury Mironyuk", "Q15966564": "Ulrich Christoph Salchow", "Q15967714": "Neva Haites", "Q15967887": "Joseph Petavel", "Q15970636": "Jean-Louis Coatrieux", "Q15975533": "Ludwig Richter", "Q15978278": "J\u00f3zef Twardowski", "Q15978859": "Pyotr Vladimirov", "Q15979722": "Jean Aubouin", "Q15980115": "Yuri Arutyunyan", "Q15981149": "Petr Spiridonovich Biljarskij", "Q15981179": "Naum Jasny", "Q15989548": "Emik Avakian", "Q15989702": "Anju Chadha", "Q15989764": "Hugh Gurling", "Q15989783": "Sivakumar Veerasamy"}