{"Q30609944": "W\u0142adys\u0142aw Satke", "Q30610128": "Yevhen-Ihor Horodetskyi", "Q30611083": "\u0130smail Hikmet Ertaylan", "Q30617108": "Rafael Meliksetyan", "Q30641573": "Stephen W. Pacala", "Q30646261": "Jean Carlet", "Q30646383": "Bernard H. Bressler", "Q30676482": "Michael A. Wheeler", "Q30692567": "Herbert A. Winkelmann", "Q30879160": "Vladimir Kostrzhitsky", "Q30879442": "Petr Butkovsky", "Q30879503": "Vitalii Maidannyk", "Q30879566": "Alexander Matveev", "Q30879599": "V. A. Sysuev", "Q30879641": "Vladimir Gorbunov", "Q30879772": "Igor Barskov", "Q27908298": "Peter Schupp", "Q27908299": "Petr P. Safronov", "Q27908301": "Petros G. Koutsoukos", "Q27908302": "Philipp Sapozhnikov", "Q27908303": "Ralf Hoffmann", "Q27908306": "Ren\u00e9 Hedrich", "Q27908307": "Roberta Galli", "Q27908308": "Roland Thielsch", "Q27908309": "Sabine Kaiser", "Q27908310": "Sascha Heinemann", "Q27908311": "Sebastian Hunoldt", "Q27908312": "Sergei Belikov", "Q27908313": "Sergey S. Golik", "Q27908314": "Sergey S. Voznesenskiy", "Q27908315": "Sergey D. Litvinov", "Q27908316": "Serguei L. Molodtsov", "Q27908317": "Serguei V. Nekipelov", "Q27908318": "Silvia Paasch", "Q27908319": "Sina Brockmann", "Q27908320": "Sophie R\u00f6\u00dfler", "Q27908321": "Stanislav Gorb", "Q27908322": "Stefano Schiaparelli", "Q27908323": "Susanne Bierbaum", "Q27908324": "Susanne Machill", "Q27908325": "Teofil Jesionowski", "Q27908326": "Thomas Behm", "Q27908327": "Thomas Hanke", "Q27908329": "Thorsten Geisler-Wierwille", "Q27908330": "Thuro Arnold", "Q27908331": "Timothy Douglas", "Q27908332": "Tobias Langrock", "Q27908333": "Ulf Roland", "Q27908334": "Ulrich Skrzypczak", "Q27908335": "Uwe Schwarzenbolz", "Q27908336": "Valentin A. Stonik", "Q27908337": "Valery P. Varlamov", "Q27908339": "Viktor N. Sivkov", "Q27908340": "Vladimir Krasokhin", "Q27908341": "Wilder Carrillo-Cabrera", "Q27908343": "Yuri N. Kulchin", "Q27908344": "Yury N. Elkin", "Q27908345": "Zden\u011bk Petr\u00e1\u0161ek", "Q27908346": "Zoran Kljajic", "Q27908773": "Anna Procyk", "Q27908810": "Daria Krylova", "Q27908870": "Uwe Gutsche", "Q27908873": "Doru C. Lupascu", "Q27908875": "J\u00fcrgen Bauch", "Q27910006": "Alexander Ivanovich Vishnyak", "Q27916119": "Athanassios Z. Panagiotopoulos", "Q27916172": "Jiban Jyoti Panda", "Q27916397": "Ajmal Khan", "Q27917459": "Satomi Soejima", "Q27918328": "Yury Ivanov", "Q27918569": "Paco C\u00e1rdenas", "Q27918744": "Enilma M. Araujo", "Q27918928": "Cristina Cede\u00f1o-Posso", "Q27919210": "Ihar Mel\u02b9nika\u016d", "Q27919216": "Alexander Alexandrovich Guzhalovsky", "Q27919827": "Robert McQuillin", "Q27920548": "Ilga Apine", "Q27922215": "Deb Shankar Ray", "Q27922313": "Maurice Green", "Q27922314": "Maurizio Prato", "Q27924805": "Siva Umapathy", "Q27924806": "Vadapalli Chandrasekhar", "Q27925011": "Richard Nichols", "Q27925975": "Viktor Malkov", "Q27927067": "V\u011bra Majerov\u00e1", "Q27929565": "Alison Tedstone", "Q27942747": "Eliane Van Alboom", "Q27943185": "Benjamin J Ainscough", "Q27947531": "Mary Ann Moran", "Q27947618": "Simon Cherry", "Q27947833": "Tetyana Kvyatkovska", "Q27969236": "Oliver Gatty", "Q27970641": "Andres Jaramillo-Botero", "Q27971068": "Tadeusz Szczurek", "Q27972775": "Jerome S. Spevack", "Q43424113": "Andrey Shebunin", "Q43424603": "Pyotr Krasnov", "Q43424849": "Aleksandr Kovalyov", "Q43425066": "Sergey Vorobyov", "Q43425097": "Aleksey Kiselyov"}