{"Q29014828": "Miriam Billig", "Q29016666": "Mirz\u0259 Sad\u0131xov", "Q29022624": "Diederik P. Kingma", "Q29023815": "Anatoly Mikhailovich Smirnov", "Q29026881": "Greg Zaric", "Q29029083": "Rashmi Shetty", "Q29033365": "David J Love", "Q29033533": "Gregory H. Botz", "Q29033873": "Bo Niklasson", "Q29034157": "Miles Taylor", "Q29035317": "Baba C. Vemuri", "Q29035326": "Guruswami Ravichandran", "Q29035338": "S. K. Ramesh", "Q29047189": "Catherine Steele", "Q29048381": "Olga Belobrova", "Q29048422": "Larisa Aksyonova", "Q29049652": "Mehdi \u0130sk\u0259nd\u0259rli", "Q29050638": "Mark S. Ghiorso", "Q29053406": "Nikola\u012d Ti\ufe20u\ufe21ti\ufe20u\ufe21lkov", "Q29054680": "Mar\u00eda Antonieta Rebollo", "Q29054987": "Jeanne E. Griffith", "Q29064663": "Vilma Rose Hunt", "Q39387056": "Leonid Yakimenko", "Q39387070": "Leanid Luksha", "Q39387100": "Leon Rogalski", "Q39387122": "Lev Berman", "Q39387139": "L. A. Mendel\u02b9son", "Q39387180": "Vladimir Kotov", "Q39387191": "Konstantin Keshishev", "Q39387217": "Konstantin Pozdniakov", "Q39387253": "Colin James Drury", "Q39387843": "Ilya Feranchuk", "Q39387905": "Igor Mishchenko", "Q39387912": "Igor Antipin", "Q39387931": "Igor Kolesnikov", "Q39388012": "Ivan Barsukov", "Q39388059": "Ivan Korsunsky", "Q39388745": "Yawheniya Kechyna", "Q39388914": "Dmitry Krasilnikov", "Q39389053": "Damir \u011e\u00f6b\u00e4ydullin", "Q39389221": "Georgy Stolyarov", "Q39389347": "Vyacheslav Kuznetsov", "Q39389374": "Vsevolod Anfilogov", "Q39389395": "Vladimir Rushanin", "Q39389430": "Vladimir Sosnovsky", "Q39389443": "Vladimir Fisenko", "Q39389515": "Vladimir Yurin", "Q39389537": "Vladimir Borzdov", "Q39389553": "Vladimir Kozlov", "Q39390117": "Vladimir Shkatulla", "Q39390130": "Vladimir Onishchenko", "Q39390135": "Vladimir Mikulovich", "Q39390146": "Vladimir Vasilyev", "Q39390153": "Vladimir Troshin", "Q39390166": "Vladimir Belov", "Q39390198": "Vladimir Dmitriyev", "Q39390205": "Vladimir Skrebitsky", "Q39390211": "Vladimir Sakhno", "Q39390223": "Vladimir Yushin", "Q39390228": "Vladimir Apanasovich", "Q39390241": "Vladimir Krylov", "Q39390245": "Vladimir Storozhev", "Q39390249": "Vladimir Mogilnyy", "Q39390270": "Vladimir Odzhaev", "Q39390314": "Vladimir Pilipenko", "Q39390396": "Viktor Gavrilov", "Q39390429": "Viktor Grigoryev", "Q39390443": "Viktor Goncharov", "Q39391034": "Vasilij Fedorovi\u010d \u010cigir", "Q39391073": "Vasily Volkov", "Q39391149": "Walter Eduardovich Schmidt", "Q39391194": "V. M.  Savit\u0361ski\u012d", "Q39391252": "Valyantsin Rusak", "Q31296449": "Valeh C\u0259f\u0259rov", "Q31296624": "Afiq H\u0259s\u0259nov", "Q31296627": "Amin \u0130smay\u0131lov", "Q31296632": "Tamella Al\u0131yeva", "Q31296647": "T\u0259l\u0259t K\u0259ng\u0259rli", "Q31296698": "X\u0259lil Qas\u0131mov", "Q31296719": "Rauf Qarda\u015fov", "Q31296751": "Nikola\u00ef Anserov", "Q31296757": "R\u00fcf\u0259t Mir-Qas\u0131mov", "Q31296764": "T\u0259rlan M\u0259mm\u0259dov", "Q31296778": "Anvar Nahmadov", "Q31296806": "Hac\u0131 F\u0259xr\u0259ddin S\u0259f\u0259rli", "Q31296814": "Tulparxan Salavatov", "Q31296825": "Ajdar Alasgarzada", "Q31296839": "Nizami Ta\u011f\u0131soy", "Q31296955": "Shamsuddin Jafarov", "Q31298529": "Dada\u015f H\u00fcseynov", "Q31298982": "Fouad Shikhiyev", "Q31299163": "Mukhtar Abduyev", "Q31299218": "\u0130smay\u0131l Q\u0259ribov", "Q31299608": "Heydar Efendiyev", "Q31299770": "Zakir Cahangirli", "Q31300238": "Orxan X\u0259lilov", "Q31300461": "C\u0259f\u0259r A\u011falarov", "Q31300497": "Elmira K\u0259rimova", "Q31300513": "Solmaz Mustafayeva", "Q31300531": "Qeylani P\u0259nahov"}