{"Q4515365": "Dmitry Chechot", "Q4515376": "Nikolay Chechulin", "Q4515409": "Marat Cheshkov", "Q4515733": "Leonid Chizhevsky", "Q4515801": "Yury Chizmadzhev", "Q4515903": "Vladimir Chikolev", "Q4516156": "Nikolay Chirvinskiy", "Q4516438": "Nikolay Chistovich", "Q4516814": "Igor Chichurov", "Q4516928": "Mikhail Chlenov", "Q4517073": "Shafik Chokin", "Q4517597": "E. A. Chudakov", "Q4517635": "Aleksandr Chudinov", "Q4517946": "Chuluuny Dala\u012d", "Q4518172": "Vladimir Churakov", "Q4518187": "Valeria Churganova", "Q4518375": "Aleksandr Chuchalin", "Q4518455": "Vyacheslav Chkhikvadze", "Q4519164": "Petr Shaboltay", "Q4519180": "Ivan Shabunin", "Q4519192": "Nikolay Shaburov", "Q4519289": "Vladislav Sjaychoelagzamovitsj Sjagapov", "Q4519340": "Johann Matthias Schaden", "Q4519394": "Viktor Gennad\u02b9evich Shadurski\u012d", "Q4519441": "Vladimir Shaydurov", "Q4519457": "Anatoly Shaykevich", "Q4519556": "Yury Shakaryan", "Q4519574": "Dzjigandar Tagirovitsj Sjakirov", "Q4519802": "Zoya Shalyapina", "Q4519877": "Ayrat Shammazov", "Q4520023": "Mikhail Shandala", "Q4520070": "Karim Shoniezov Shoniezovich", "Q4520191": "Maksim Shapir", "Q4520196": "Aleksandr Shapiro", "Q4520269": "Viktor Shapoval", "Q4520317": "Aleksandr Shaposhnikov", "Q4266083": "Viktor Lomakin", "Q4266159": "Boris Lomberg", "Q4266175": "Georgy Lomidze", "Q4266221": "Aleksandr Lomov", "Q4266223": "Anatoly Lomov", "Q4266605": "Vladimir Lopatin", "Q4266793": "Vitaly Lopota", "Q4267782": "Vladimir Lubovsky", "Q4268722": "Viktor Lukachiov", "Q4268881": "Nikolay Lukin", "Q4269192": "Anatoly Lukyanov", "Q4269550": "Lazar Lunts", "Q4269574": "Vladimir Lunyov", "Q4269650": "Polina Lupinskaya", "Q4269712": "Roman Luriya", "Q4269731": "Leonid Lurye", "Q4270139": "Viktor Luchin", "Q4270161": "Nikolay Luchinsky", "Q4270675": "Sofya Lysenkova", "Q4270938": "Andrey Lvov", "Q4271346": "Matvey Lyubavsky", "Q4271377": "Valery Lyubartovich", "Q4271501": "Grigory Lyubimov", "Q4271701": "Pavel Lyublinsky", "Q4272267": "Victor Alexeevich Lyusov", "Q4272357": "Alexander Lyutkevich", "Q4272402": "Anatoly Lyuty", "Q4272898": "Boris Lyovin", "Q4273075": "Sergey Lyozov", "Q4273808": "Midkhat Mavlyutov", "Q4273818": "Abdyrakhman Mavlyanov", "Q4273883": "Basyr Magadeyev", "Q4274148": "Madrudin Magomed-Eminov", "Q4274171": "Murad Magomedov", "Q4274175": "Rabadan Magomedov", "Q4274181": "Aleksandr Magometov", "Q4274207": "Jeffrey Kaplan", "Q4274586": "Viktor Mazunov", "Q4274593": "V. B. Mazur", "Q4274627": "Aleksey Mazurov", "Q4274628": "Anatoly Mazurov", "Q4275162": "Valery Maystrenko", "Q4275169": "Nikolay Maysuryan", "Q4275350": "Vasily Makarov", "Q4275357": "Vladimir Makarov", "Q4275361": "Grigory Makarov", "Q4275371": "Igor Mikhajlovich Makarov", "Q4275388": "Nikolai Makarov", "Q4275420": "Nikolai Makarovets", "Q4275611": "Samuel McGredy IV", "Q4275612": "Samuel McGredy II", "Q4275613": "Samuel Davison McGredy III", "Q4275882": "Aleksandr Makovelski", "Q4275960": "Jane Dammen McAuliffe", "Q4276286": "Sergey Maksimovich", "Q4276410": "Nazjiba Haerzamanovna Maksjutova", "Q4276587": "Valerii Malakhov", "Q4276624": "Kim Malakhovsky", "Q4276661": "Lyubov Mala", "Q4277713": "Nikolay Maletin", "Q4277716": "Hryhoriy Matets", "Q4277782": "Aleksandr Malinin", "Q4277787": "Vasily Malinin", "Q4277797": "Nikolay Malinin"}