{"Q12842764": "M\u0259mm\u0259d\u0259li Meyb\u0259liyev", "Q12842767": "M\u0259mm\u0259d\u0259li M\u00fcs\u0259ddiq", "Q12842822": "M\u0259nz\u0259r\u0259 M\u0259mm\u0259dova", "Q12842826": "M\u0259qs\u0259d Qocamanov", "Q12842827": "M\u0259qs\u0259d S\u0259ttarov", "Q12842832": "M\u0259rdan Muradxanov", "Q12842847": "M\u0259ry\u0259m Mahmudb\u0259yova", "Q12842854": "Maryam Seyidbeyli", "Q12842856": "M\u0259ry\u0259m \u018flizad\u0259", "Q12842860": "M\u0259sia\u011fa M\u0259h\u0259mm\u0259di", "Q12843026": "Nahad \u018fliyev", "Q12843031": "Naid\u0259 M\u0259mm\u0259dxanova", "Q12843070": "Namiq N\u0259srullayev", "Q12843072": "Namiq \u018fhm\u0259dov", "Q12843110": "Natiq Cavadov", "Q12843184": "Nazim Aslan Bozalqanl\u0131", "Q12843206": "Nazim Afandiyev", "Q12843207": "Nazim \u0130manov", "Q12843208": "Nazim \u015eamilov", "Q12843262": "Nem\u0259tullah Nax\u00e7\u0131vani", "Q12843338": "Niyazi Mehdi", "Q12843339": "Niyazi \u0130sayev", "Q12843348": "Nizami Mehdiyev", "Q12843354": "Nizami Xudiyev", "Q12843359": "Nizami V\u0259liyev", "Q12843373": "Nizam\u0259ddin \u015e\u0259msizad\u0259", "Q12843439": "Nuru M\u0259mm\u0259dov", "Q12843487": "N\u0259c\u0259f N\u0259c\u0259fov", "Q12843570": "N\u0259sr\u0259ddin Qarayev", "Q12843667": "Oqtay M\u0259likov", "Q12843673": "Oqtay Rza", "Q12844068": "P\u0259nah Qurbanov", "Q12844071": "P\u0259nah X\u0259lilov", "Q12844118": "Qafar K\u0259ndli", "Q12844153": "Qaley Allahverdiyev", "Q12844163": "Qalib \u0130manov", "Q7348305": "Hashim Yaacob", "Q7348832": "Robert Pepper", "Q7349816": "Robert Singerman", "Q7349836": "Robert Slade", "Q7349919": "Robert Sonkin", "Q7351763": "Roberto Kolter", "Q7353745": "Ismail Hussein", "Q7358061": "Roger D. Nelson", "Q7358262": "Roger Gregory", "Q7358489": "Roger L. Easton", "Q7362266": "Roman Zubarev", "Q7364859": "Ronald Finn", "Q7364937": "Ronald Hinchcliffe", "Q7365136": "Ronald N. Hartman", "Q7365353": "Ronald V. Schmidt", "Q7365367": "Ronald W. Yeung", "Q7365598": "Ronen Avraham", "Q7368958": "Rosina M. Bierbaum", "Q7369491": "Ross Masood", "Q7369640": "Ross S. Stein", "Q7369954": "Rostam Gorgani", "Q7372513": "Roy Alexander Weagant", "Q7372637": "Roy C. Newton", "Q7372849": "Roy Gordon Grainger", "Q7376401": "Ruby Umesh Pawankar", "Q7377432": "Rudolph Leibel", "Q7377487": "Rudolphina Menzel", "Q7377598": "Rudy Dekeyser", "Q7378013": "Rufus Carrollton Harris", "Q7381592": "Russell J. Howard", "Q7381847": "Russell W. Kruse", "Q7381886": "Russell Zguta", "Q7382640": "Rusty Roberts", "Q7387591": "S. K. Shivakumar", "Q7387754": "S. P. Sudrania", "Q7388703": "Mohd. Taib Osman", "Q7395792": "Saba Soomekh", "Q7397675": "Saddek Rabah", "Q7397798": "Sadek Hilal", "Q7398244": "Saeed Reza Ghaffari", "Q7403873": "Saleemul Huq", "Q7408025": "Sam Porcello", "Q7408361": "Sam Wyly", "Q7409041": "Sambhu Nath De", "Q7411686": "Samuel Hibben", "Q7412417": "Samuel Prescott Hildreth", "Q7412761": "Samuel Tertius Galton", "Q7417487": "Sandy Stevens Tickodri-Togboa", "Q7417640": "Sanford Levinson", "Q7420211": "Santiago Americano Freire", "Q7426831": "Saturnin Zawadzki", "Q7437103": "Scott Ransom", "Q7441100": "Sean J. Morrison", "Q7448872": "Selvin Christopher", "Q7448980": "Sema Sgaier", "Q7453603": "Sergei Kruchinin", "Q7461296": "Shah M. Faruque", "Q7461315": "Shah Muhammad Sulaiman", "Q7462398": "Shaig Asgarov", "Q7463103": "Osamu Hashimoto", "Q7493480": "Sheldon E. Isakoff", "Q7493827": "V. I. Avdiev", "Q7495200": "Sherman Jackson", "Q7495275": "Sherman Wu"}